consoletabletext/__init__.py
consoletabletext/console.py
consoletabletext/example.py
consoletabletext-1.0.2.dist-info/METADATA
consoletabletext-1.0.2.dist-info/WHEEL
consoletabletext-1.0.2.dist-info/licenses/LICENSE
consoletabletext-1.0.2.dist-info/RECORD
