Metadata-Version: 2.1
Name: ConsoleTableText
Version: 1.0.2
Summary: Console Table Test is a Python package that will help you output messages to the console in a console with adaptive message length change
Project-URL: Homepage, https://github.com/Blackdog7777/ConsoleTableText
Project-URL: Bug Tracker, https://github.com/Blackdog7777/ConsoleTableText/issues
Author-email: BlackDog <amalia.c.camalia@gmail.com>
License: Copyright (c) 2018 The Python Packaging Authority
Classifier: License :: OSI Approved :: MIT License
Classifier: Operating System :: OS Independent
Classifier: Programming Language :: Python :: 3
Requires-Python: >=3.6
